dria_agent/__init__.py
dria_agent/__main__.py
dria_agent/agent/__init__.py
dria_agent/agent/agent.py
dria_agent/agent/checkers.py
dria_agent/agent/clients/api.py
dria_agent/agent/clients/apic.py
dria_agent/agent/clients/base.py
dria_agent/agent/clients/hfc.py
dria_agent/agent/clients/mlxc.py
dria_agent/agent/clients/ollmc.py
dria_agent/agent/embedder.py
dria_agent/agent/mcp/__init__.py
dria_agent/agent/mcp/client.py
dria_agent/agent/mcp/config.py
dria_agent/agent/mcp/tool_adapter.py
dria_agent/agent/settings/prompt.py
dria_agent/agent/settings/providers.py
dria_agent/agent/tool.py
dria_agent/agent/utils.py
dria_agent/agent/vdb.py
dria_agent/pythonic/__init__.py
dria_agent/pythonic/engine.py
dria_agent/pythonic/schemas.py
dria_agent/pythonic/util.py
dria_agent/tools/__init__.py
dria_agent/tools/library/__init__.py
dria_agent/tools/library/api_tools.py
dria_agent/tools/library/apple_tools/__init__.py
dria_agent/tools/library/apple_tools/apple_tools.py
dria_agent/tools/library/apple_tools/cmd.py
dria_agent/tools/library/docker_tools.py
dria_agent/tools/library/github_tools.py
dria_agent/tools/library/math_tools.py
dria_agent/tools/library/search_tools.py
dria_agent/tools/library/slack_tools.py
dria_agent-0.1.59.dist-info/LICENSE
dria_agent-0.1.59.dist-info/METADATA
dria_agent-0.1.59.dist-info/WHEEL
dria_agent-0.1.59.dist-info/entry_points.txt
dria_agent-0.1.59.dist-info/RECORD
