Metadata-Version: 2.3
Name: dria_agent
Version: 0.1.59
Summary: speedy, performant and small tool calling agents
License: MIT
Author: andthattoo
Author-email: omer@firstbatch.xyz
Requires-Python: >=3.12,<4.0
Classifier: License :: OSI Approved :: MIT License
Classifier: Programming Language :: Python :: 3
Classifier: Programming Language :: Python :: 3.12
Classifier: Programming Language :: Python :: 3.13
Provides-Extra: huggingface
Provides-Extra: mcp
Provides-Extra: mlx
Provides-Extra: tools
Requires-Dist: beautifulsoup4 (>=4.13.3,<5.0.0) ; extra == "tools"
Requires-Dist: docker (>=7.1.0,<8.0.0) ; extra == "tools" or extra == "tools"
Requires-Dist: duckduckgo-search (>=7.3.2,<8.0.0) ; extra == "tools"
Requires-Dist: markdownify (>=0.14.1,<0.15.0) ; extra == "tools"
Requires-Dist: mcp (>=1.3.0,<2.0.0) ; extra == "mcp"
Requires-Dist: mlx (>=0.22.1,<0.23.0) ; extra == "mlx"
Requires-Dist: mlx-lm (>=0.21.4,<0.22.0) ; extra == "mlx"
Requires-Dist: numpy (>=2.2.2,<3.0.0)
Requires-Dist: ollama (>=0.4.7,<0.5.0)
Requires-Dist: openai (>=1.61.1,<2.0.0)
Requires-Dist: pygithub (>=2.6.0,<3.0.0) ; extra == "tools"
Requires-Dist: requests (>=2.32.3,<3.0.0)
Requires-Dist: rich (>=13.9.4,<14.0.0)
Requires-Dist: scikit-learn (>=1.6.1,<2.0.0) ; extra == "tools"
Requires-Dist: sentence-transformers (>=3.4.1,<4.0.0) ; extra == "huggingface" or extra == "mlx"
Requires-Dist: slack-sdk (>=3.34.0,<4.0.0) ; extra == "tools"
Requires-Dist: smolagents (>=1.8.1,<2.0.0) ; extra == "tools"
Requires-Dist: transformers (>=4.48.3,<5.0.0) ; extra == "huggingface"
Requires-Dist: urllib3 (>=2.3.0,<3.0.0)
